mcp_background_job/__init__.py
mcp_background_job/__main__.py
mcp_background_job/config.py
mcp_background_job/logging_config.py
mcp_background_job/models.py
mcp_background_job/process.py
mcp_background_job/server.py
mcp_background_job/service.py
mcp_background_job-0.1.2.dist-info/METADATA
mcp_background_job-0.1.2.dist-info/WHEEL
mcp_background_job-0.1.2.dist-info/entry_points.txt
mcp_background_job-0.1.2.dist-info/RECORD
