Metadata-Version: 2.4
Name: mcp-background-job
Version: 0.1.2
Summary: MCP server for executing long-running shell commands asynchronously
Project-URL: Homepage, https://github.com/dylan-gluck/mcp-background-job
Project-URL: Repository, https://github.com/dylan-gluck/mcp-background-job
Project-URL: Issues, https://github.com/dylan-gluck/mcp-background-job/issues
Author-email: Dylan Navajas Gluck <dylan.n.gluck@gmail.com>
License: MIT
Keywords: async,background,commands,jobs,mcp,shell
Classifier: Development Status :: 4 - Beta
Classifier: Intended Audience :: Developers
Classifier: License :: OSI Approved :: MIT License
Classifier: Programming Language :: Python :: 3
Classifier: Programming Language :: Python :: 3.12
Requires-Python: >=3.12
Requires-Dist: fastmcp>=2.11.1
Requires-Dist: pydantic>=2.11.7
